setup.py
tpList/__init__.py
tpList.egg-info/PKG-INFO
tpList.egg-info/SOURCES.txt
tpList.egg-info/dependency_links.txt
tpList.egg-info/top_level.txt