Metadata-Version: 1.0
Name: tpList
Version: 0.0.3
Summary: 递归打印
Home-page: https://github.com/2lovecode/
Author: 2lovecode
Author-email: liu546hao@163.com
License: UNKNOWN
Platform: UNKNOWN
